ExcelRobot/__init__.py
ExcelRobot/base.py
ExcelRobot/reader.py
ExcelRobot/utils.py
ExcelRobot/version.py
ExcelRobot/writer.py
robotframework_excel-1.0.0b4.data/data/ExcelRobotTest/ExcelRobot.html
robotframework_excel-1.0.0b4.data/data/ExcelRobotTest/release-notes.md
robotframework_excel-1.0.0b4.dist-info/DESCRIPTION.rst
robotframework_excel-1.0.0b4.dist-info/METADATA
robotframework_excel-1.0.0b4.dist-info/RECORD
robotframework_excel-1.0.0b4.dist-info/WHEEL
robotframework_excel-1.0.0b4.dist-info/metadata.json
robotframework_excel-1.0.0b4.dist-info/top_level.txt
tests/unit/__init__.py
tests/unit/test_data_format.py
tests/unit/test_reader.py
tests/unit/test_writer.py
